quizicist/__init__.py
quizicist/completion.py
quizicist/consts.py
quizicist/errors.py
quizicist/postprocess.py
quizicist/prompt.py
quizicist-0.1.0.dist-info/LICENSE
quizicist-0.1.0.dist-info/METADATA
quizicist-0.1.0.dist-info/WHEEL
quizicist-0.1.0.dist-info/top_level.txt
quizicist-0.1.0.dist-info/RECORD
